<annotation>
	<folder></folder>
	<filename>Normal_Brain_400_jpg.rf.7d5fb72e8d5ee72ef9874cbcd16406f9.jpg</filename>
	<path>Normal_Brain_400_jpg.rf.7d5fb72e8d5ee72ef9874cbcd16406f9.jpg</path>
	<source>
		<database>roboflow.com</database>
	</source>
	<size>
		<width>177</width>
		<height>197</height>
		<depth>3</depth>
	</size>
	<segmented>0</segmented>
	<object>
		<name>Normal_Brain</name>
		<pose>Unspecified</pose>
		<truncated>0</truncated>
		<difficult>0</difficult>
		<occluded>0</occluded>
		<bndbox>
			<xmin>8</xmin>
			<xmax>178</xmax>
			<ymin>1</ymin>
			<ymax>198</ymax>
		</bndbox>
		<polygon>
			<x1>177</x1>
			<y1>0.08</y1>
			<x2>6.62</x2>
			<y2>0.08</y2>
			<x3>6.62</x3>
			<y3>197</y3>
			<x4>177</x4>
			<y4>197</y4>
			<x5>177</x5>
			<y5>0.08</y5>
		</polygon>
	</object>
	<metadata>
	</metadata>
</annotation>
