<annotation>
	<folder></folder>
	<filename>Tumour-Meningioma_529_jpg.rf.df315a83458bc77d8100243a58b00f82.jpg</filename>
	<path>Tumour-Meningioma_529_jpg.rf.df315a83458bc77d8100243a58b00f82.jpg</path>
	<source>
		<database>roboflow.com</database>
	</source>
	<size>
		<width>508</width>
		<height>508</height>
		<depth>3</depth>
	</size>
	<segmented>0</segmented>
	<object>
		<name>Tumour-Pituitary</name>
		<pose>Unspecified</pose>
		<truncated>0</truncated>
		<difficult>0</difficult>
		<occluded>0</occluded>
		<bndbox>
			<xmin>129</xmin>
			<xmax>245</xmax>
			<ymin>148</ymin>
			<ymax>294</ymax>
		</bndbox>
		<polygon>
			<x1>244.2</x1>
			<y1>146.935</y1>
			<x2>127.92</x2>
			<y2>146.935</y2>
			<x3>127.92</x3>
			<y3>293.205</y3>
			<x4>244.2</x4>
			<y4>293.205</y4>
			<x5>244.2</x5>
			<y5>146.935</y5>
		</polygon>
	</object>
	<metadata>
	</metadata>
</annotation>
