<annotation>
	<folder></folder>
	<filename>Tumour-Pituitary_494_jpg.rf.e0c664093476d127bde64ce121e9f13d.jpg</filename>
	<path>Tumour-Pituitary_494_jpg.rf.e0c664093476d127bde64ce121e9f13d.jpg</path>
	<source>
		<database>roboflow.com</database>
	</source>
	<size>
		<width>488</width>
		<height>488</height>
		<depth>3</depth>
	</size>
	<segmented>0</segmented>
	<object>
		<name>Tumour-Pituitary</name>
		<pose>Unspecified</pose>
		<truncated>0</truncated>
		<difficult>0</difficult>
		<occluded>0</occluded>
		<bndbox>
			<xmin>234</xmin>
			<xmax>291</xmax>
			<ymin>276</ymin>
			<ymax>339</ymax>
		</bndbox>
		<polygon>
			<x1>290.43</x1>
			<y1>275.26</y1>
			<x2>232.83</x2>
			<y2>275.26</y2>
			<x3>232.83</x3>
			<y3>337.64</y3>
			<x4>290.43</x4>
			<y4>337.64</y4>
			<x5>290.43</x5>
			<y5>275.26</y5>
		</polygon>
	</object>
	<metadata>
	</metadata>
</annotation>
