<annotation>
	<folder></folder>
	<filename>Tumour-Pituitary_11_jpg.rf.49e8b97080b61dcd9d6638dda95bfd0b.jpg</filename>
	<path>Tumour-Pituitary_11_jpg.rf.49e8b97080b61dcd9d6638dda95bfd0b.jpg</path>
	<source>
		<database>roboflow.com</database>
	</source>
	<size>
		<width>506</width>
		<height>506</height>
		<depth>3</depth>
	</size>
	<segmented>0</segmented>
	<object>
		<name>Tumour-Pituitary</name>
		<pose>Unspecified</pose>
		<truncated>0</truncated>
		<difficult>0</difficult>
		<occluded>0</occluded>
		<bndbox>
			<xmin>239</xmin>
			<xmax>271</xmax>
			<ymin>188</ymin>
			<ymax>222</ymax>
		</bndbox>
		<polygon>
			<x1>270.13</x1>
			<y1>187.135</y1>
			<x2>237.53</x2>
			<y2>187.135</y2>
			<x3>237.53</x3>
			<y3>221.385</y3>
			<x4>270.13</x4>
			<y4>221.385</y4>
			<x5>270.13</x5>
			<y5>187.135</y5>
		</polygon>
	</object>
	<metadata>
	</metadata>
</annotation>
