<annotation>
	<folder></folder>
	<filename>Tumour-Glioma_302_jpg.rf.8a36ceced31b8f31bf68bfba74f3ed94.jpg</filename>
	<path>Tumour-Glioma_302_jpg.rf.8a36ceced31b8f31bf68bfba74f3ed94.jpg</path>
	<source>
		<database>roboflow.com</database>
	</source>
	<size>
		<width>512</width>
		<height>512</height>
		<depth>3</depth>
	</size>
	<segmented>0</segmented>
	<object>
		<name>Tumour-Glioma</name>
		<pose>Unspecified</pose>
		<truncated>0</truncated>
		<difficult>0</difficult>
		<occluded>0</occluded>
		<bndbox>
			<xmin>189</xmin>
			<xmax>276</xmax>
			<ymin>205</ymin>
			<ymax>295</ymax>
		</bndbox>
		<polygon>
			<x1>275</x1>
			<y1>203.585</y1>
			<x2>188</x2>
			<y2>203.585</y2>
			<x3>188</x3>
			<y3>293.995</y3>
			<x4>275</x4>
			<y4>293.995</y4>
			<x5>275</x5>
			<y5>203.585</y5>
		</polygon>
	</object>
	<metadata>
	</metadata>
</annotation>
