<annotation>
	<folder></folder>
	<filename>Tumour-Glioma_13_jpg.rf.6d03c40d25fd4c2b1ce1b48f52f99727.jpg</filename>
	<path>Tumour-Glioma_13_jpg.rf.6d03c40d25fd4c2b1ce1b48f52f99727.jpg</path>
	<source>
		<database>roboflow.com</database>
	</source>
	<size>
		<width>480</width>
		<height>480</height>
		<depth>3</depth>
	</size>
	<segmented>0</segmented>
	<object>
		<name>Tumour-Glioma</name>
		<pose>Unspecified</pose>
		<truncated>0</truncated>
		<difficult>0</difficult>
		<occluded>0</occluded>
		<bndbox>
			<xmin>326</xmin>
			<xmax>398</xmax>
			<ymin>115</ymin>
			<ymax>201</ymax>
		</bndbox>
		<polygon>
			<x1>396.56</x1>
			<y1>114.195</y1>
			<x2>324.66</x2>
			<y2>114.195</y2>
			<x3>324.66</x3>
			<y3>200.105</y3>
			<x4>396.56</x4>
			<y4>200.105</y4>
			<x5>396.56</x5>
			<y5>114.195</y5>
		</polygon>
	</object>
	<metadata>
	</metadata>
</annotation>
